odyssey/ai/model/__init__.py
odyssey/ai/model/cloud/__init__.py
odyssey/ai/model/cloud/configuracion/Configuracion.py
odyssey/ai/model/cloud/configuracion/__init__.py
odyssey/ai/model/cloud/core/__init__.py
odyssey/ai/model/cloud/core/db/Database.py
odyssey/ai/model/cloud/core/db/DatabaseAWS.py
odyssey/ai/model/cloud/core/db/DatabaseAWSPostgreSQL.py
odyssey/ai/model/cloud/core/db/__init__.py
odyssey/ai/model/cloud/core/db/utilidades_bd.py
odyssey/ai/model/cloud/core/handlers/Error_Handler.py
odyssey/ai/model/cloud/core/handlers/__init__.py
odyssey/ai/model/cloud/core/log/Level.py
odyssey/ai/model/cloud/core/log/Log.py
odyssey/ai/model/cloud/core/log/__init__.py
odyssey/ai/model/cloud/core/models/CodigosRespuesta.py
odyssey/ai/model/cloud/core/models/DB.py
odyssey/ai/model/cloud/core/models/Daos.py
odyssey/ai/model/cloud/core/models/TipoConsulta.py
odyssey/ai/model/cloud/core/models/TipoInputOutput.py
odyssey/ai/model/cloud/core/models/__init__.py
odyssey/ai/model/cloud/core/seguridad/Apigee.py
odyssey/ai/model/cloud/core/seguridad/Crypto.py
odyssey/ai/model/cloud/core/seguridad/LlavesCobranza.py
odyssey/ai/model/cloud/core/seguridad/Middleware.py
odyssey/ai/model/cloud/core/seguridad/MiddlewareApigee.py
odyssey/ai/model/cloud/core/seguridad/__init__.py
odyssey/ai/model/cloud/core/utilerias/Cadenas.py
odyssey/ai/model/cloud/core/utilerias/Constantes.py
odyssey/ai/model/cloud/core/utilerias/Request.py
odyssey/ai/model/cloud/core/utilerias/Web.py
odyssey/ai/model/cloud/core/utilerias/__init__.py
odyssey/ai/model/cloud/core/utilerias/math.py
odysseyaimodel-0.0.1.dist-info/licenses/LICENSE.txt
odysseyaimodel-0.0.1.dist-info/METADATA
odysseyaimodel-0.0.1.dist-info/WHEEL
odysseyaimodel-0.0.1.dist-info/top_level.txt
odysseyaimodel-0.0.1.dist-info/RECORD
