Metadata-Version: 2.4
Name: odysseyaimodel
Version: 0.0.1
Home-page: http://devops:9001
Author: AIT
Author-email: noreply@odysseyaimodel.com
License: License :: OSI Approved :: MIT License
Keywords: Odyssey,Cobranza,Cloud,Python,Template,Rest,Core,odyssey,odysseyai,odysseyaimodel
Classifier: Development Status :: 3 - Alpha
Classifier: Intended Audience :: Education
Classifier: Programming Language :: Python :: 2
Classifier: Programming Language :: Python :: 3
Classifier: Operating System :: MacOS :: MacOS X
Classifier: Operating System :: Microsoft :: Windows
License-File: LICENSE.txt
Requires-Dist: requests
Requires-Dist: pycryptodome
Requires-Dist: paprika
Requires-Dist: json-encoder
Requires-Dist: pyctuator
Requires-Dist: python-dotenv
Requires-Dist: starlette
Requires-Dist: pytest-cov
Requires-Dist: pytest
Requires-Dist: pytz
Requires-Dist: oracledb
Requires-Dist: httpx
Requires-Dist: PyJWT
Requires-Dist: python-dotenv
Requires-Dist: json-encoder
Requires-Dist: boto3
Requires-Dist: psycopg2-binary
Dynamic: author
Dynamic: author-email
Dynamic: classifier
Dynamic: home-page
Dynamic: keywords
Dynamic: license
Dynamic: license-file
Dynamic: requires-dist
